[
    {
        "svg": "/assets/icons/user.svg",
        "routerLink": "/institucional/nuestro-staff",
        "component": "Nuestro staff",
        "phrase": ""
    },
    {
        "svg": "/assets/icons/services.svg",
        "routerLink": "/institucional/servicios",
        "component": "Nuestros servicios",
        "phrase": ""
    },
    {
        "svg": "/assets/icons/location.svg",
        "routerLink": "/institucional/direccion",
        "component": "Encontranos",
        "phrase": ""
    },
    {
        "svg": "/assets/icons/contact.svg",
        "routerLink": "/institucional/contacto",
        "component": "Contacto",
        "phrase": ""
    }
]